{
  "updated": "2026-04-25T20:25:59Z",
  "conditions": {
    "current": {
      "level": 5.21,
      "flow": 3750.0,
      "flood_stage": 8.0,
      "pct": 65.1,
      "status": "warning",
      "label": "Caution"
    },
    "jacksfork": {
      "level": 2.57,
      "flow": 475.0,
      "flood_stage": 7.0,
      "pct": 36.7,
      "status": "safe",
      "label": "Good"
    },
    "elevenpoint": {
      "level": 0.86,
      "flow": 338.0,
      "flood_stage": 9.0,
      "pct": 9.6,
      "status": "safe",
      "label": "Good"
    },
    "niangua": {
      "level": 2.57,
      "flow": 402.0,
      "flood_stage": 12.0,
      "pct": 21.4,
      "status": "safe",
      "label": "Good"
    },
    "gasconade": {
      "level": 5.94,
      "flow": 2600.0,
      "flood_stage": 18.0,
      "pct": 33.0,
      "status": "safe",
      "label": "Good"
    },
    "meramec": {
      "level": 3.66,
      "flow": 314.0,
      "flood_stage": 20.0,
      "pct": 18.3,
      "status": "safe",
      "label": "Good"
    },
    "bigpiney": {
      "level": 10.9,
      "flow": 26700.0,
      "flood_stage": 10.0,
      "pct": 109.0,
      "status": "danger",
      "label": "Danger"
    },
    "roubidoux": {
      "level": 13.84,
      "flow": 26700.0,
      "flood_stage": 8.0,
      "pct": 173.0,
      "status": "danger",
      "label": "Danger"
    },
    "bourbeuse": {
      "level": 2.84,
      "flow": 404.0,
      "flood_stage": 16.0,
      "pct": 17.8,
      "status": "safe",
      "label": "Good"
    },
    "huzzah": {
      "level": 4.51,
      "flow": 439.0,
      "flood_stage": 7.0,
      "pct": 64.4,
      "status": "warning",
      "label": "Caution"
    }
  }
}